odoo/addons/web_ir_actions_close_wizard_refresh_view/README.rst
odoo/addons/web_ir_actions_close_wizard_refresh_view/__init__.py
odoo/addons/web_ir_actions_close_wizard_refresh_view/__manifest__.py
odoo/addons/web_ir_actions_close_wizard_refresh_view/i18n/ca.po
odoo/addons/web_ir_actions_close_wizard_refresh_view/i18n/es.po
odoo/addons/web_ir_actions_close_wizard_refresh_view/i18n/pt_BR.po
odoo/addons/web_ir_actions_close_wizard_refresh_view/i18n/web_ir_actions_close_wizard_refresh_view.pot
odoo/addons/web_ir_actions_close_wizard_refresh_view/readme/DESCRIPTION.rst
odoo/addons/web_ir_actions_close_wizard_refresh_view/readme/USAGE.rst
odoo/addons/web_ir_actions_close_wizard_refresh_view/static/description/icon.png
odoo/addons/web_ir_actions_close_wizard_refresh_view/static/description/index.html
odoo/addons/web_ir_actions_close_wizard_refresh_view/static/src/js/web_ir_actions_close_wizard_refresh_view.js
odoo/addons/web_ir_actions_close_wizard_refresh_view/templates/assets.xml
odoo12_addon_web_ir_actions_close_wizard_refresh_view-12.0.1.0.1.dist-info/METADATA
odoo12_addon_web_ir_actions_close_wizard_refresh_view-12.0.1.0.1.dist-info/WHEEL
odoo12_addon_web_ir_actions_close_wizard_refresh_view-12.0.1.0.1.dist-info/top_level.txt
odoo12_addon_web_ir_actions_close_wizard_refresh_view-12.0.1.0.1.dist-info/RECORD
