Metadata-Version: 2.1
Name: odoo12-addon-web-ir-actions-close-wizard-refresh-view
Version: 12.0.1.0.1
Summary: Allow to refresh view data without reload the page.
Home-page: https://github.com/OCA/webweb_ir_actions_close_wizard_refresh_view
Author: LevelPrime srl, Odoo Community Association (OCA)
Author-email: support@odoo-community.org
License: AGPL-3
Platform: UNKNOWN
Classifier: Programming Language :: Python
Classifier: Framework :: Odoo
Classifier: Framework :: Odoo :: 12.0
Classifier: License :: OSI Approved :: GNU Affero General Public License v3
Classifier: Development Status :: 4 - Beta
Requires-Python: >=3.5
Requires-Dist: odoo (<12.1dev,>=12.0a)
